treegrad/__init__.py
treegrad/tree_utils.py
treegrad/treegrad.py
treegrad/version.py
treegrad-1.0.1.dist-info/METADATA
treegrad-1.0.1.dist-info/RECORD
treegrad-1.0.1.dist-info/WHEEL
treegrad-1.0.1.dist-info/top_level.txt
