Metadata-Version: 2.1
Name: treegrad
Version: 1.0.1
Summary: transfer parameters from lightgbm to differentiable decision trees!
Home-page: http://github.com/chappers/TreeGrad
Author: Chapman Siu
Author-email: chpmn.siu@gmail.com
License: UNKNOWN
Platform: UNKNOWN
Requires-Python: >=3.5
Provides-Extra: complete
Provides-Extra: development
Requires-Dist: autograd
Requires-Dist: sklearn
Requires-Dist: lightgbm
Provides-Extra: complete
Requires-Dist: awscli (>=1.15.26); extra == 'complete'
Requires-Dist: coverage (>=4.5.1); extra == 'complete'
Requires-Dist: flake8 (>=3.5.0); extra == 'complete'
Requires-Dist: m2r; extra == 'complete'
Requires-Dist: nbsphinx (>=0.3.3); extra == 'complete'
Requires-Dist: nose2 (>=0.7.4); extra == 'complete'
Requires-Dist: nose2-html-report (>=0.6.0); extra == 'complete'
Requires-Dist: pandoc (>=1.0.2); extra == 'complete'
Requires-Dist: sphinx (>=1.6.6); extra == 'complete'
Requires-Dist: sphinxcontrib-napoleon (>=0.6.1); extra == 'complete'
Provides-Extra: development
Requires-Dist: sphinx (>=1.6.6); extra == 'development'
Requires-Dist: sphinxcontrib-napoleon (>=0.6.1); extra == 'development'
Requires-Dist: pandoc (>=1.0.2); extra == 'development'
Requires-Dist: nbsphinx (>=0.3.3); extra == 'development'
Requires-Dist: nose2 (>=0.7.4); extra == 'development'
Requires-Dist: nose2-html-report (>=0.6.0); extra == 'development'
Requires-Dist: coverage (>=4.5.1); extra == 'development'
Requires-Dist: awscli (>=1.15.26); extra == 'development'
Requires-Dist: flake8 (>=3.5.0); extra == 'development'
Requires-Dist: m2r; extra == 'development'
